django_pipedrive/__init__.py
django_pipedrive/settings.py
django_pipedrive/urls.py
django_pipedrive/wsgi.py
django_pipedrive2-0.1.0.dist-info/DESCRIPTION.rst
django_pipedrive2-0.1.0.dist-info/METADATA
django_pipedrive2-0.1.0.dist-info/RECORD
django_pipedrive2-0.1.0.dist-info/WHEEL
django_pipedrive2-0.1.0.dist-info/metadata.json
django_pipedrive2-0.1.0.dist-info/top_level.txt
pipedrive/__init__.py
pipedrive/fields.py
pipedrive/models.py
pipedrive/pipedrive_client.py
pipedrive/tests.py
pipedrive/urls.py
pipedrive/utils.py
pipedrive/views.py
pipedrive/migrations/0001_initial.py
pipedrive/migrations/0002_auto_20170423_2217.py
pipedrive/migrations/0003_fieldmodification.py
pipedrive/migrations/0004_auto_20170502_1701.py
pipedrive/migrations/0005_auto_20170510_1253.py
pipedrive/migrations/0006_auto_20170512_1945.py
pipedrive/migrations/0007_auto_20170519_0052.py
pipedrive/migrations/0008_auto_20170530_1548.py
pipedrive/migrations/0009_enumfield.py
pipedrive/migrations/__init__.py
test_app/__init__.py
test_app/admin.py
test_app/models.py
test_app/tests.py
test_app/views.py
test_app/migrations/0001_initial.py
test_app/migrations/__init__.py
